strictaccess/__init__.py
strictaccess/access_tags.py
strictaccess/core.py
strictaccess/decorators.py
strictaccess/exceptions.py
strictaccess-0.1.2.dist-info/licenses/LICENSE
strictaccess-0.1.2.dist-info/METADATA
strictaccess-0.1.2.dist-info/WHEEL
strictaccess-0.1.2.dist-info/top_level.txt
strictaccess-0.1.2.dist-info/RECORD
