Metadata-Version: 2.4
Name: strictaccess
Version: 0.1.2
Summary: Enforces strict access control for Python classes, with strict mode and access decorators.
Home-page: https://github.com/jhoelperaltap/strictaccess
Author: Jhoel Peralta
Author-email: jhoelperaltap@gmail.com
License: MIT
Classifier: Programming Language :: Python :: 3
Classifier: License :: OSI Approved :: MIT License
Classifier: Operating System :: OS Independent
Requires-Python: >=3.7
License-File: LICENSE
Dynamic: author
Dynamic: author-email
Dynamic: classifier
Dynamic: description
Dynamic: description-content-type
Dynamic: home-page
Dynamic: license
Dynamic: license-file
Dynamic: requires-python
Dynamic: summary
